{
    "id": 1,
    "name": "JDBC Quiz 1",
    "description": "JDBC Quiz 1",
    "questions": [
        {
            "id": 1010,
            "name": " In order to transfer data between a database and an application written in the Java programming language, the JDBC API provides which of these methods?",
			"explanation": "no explanation",
            "questionTypeId": 1,
            "options": [
                {
                    "id": 1055,
                    "questionId": 1010,
                    "name": "Methods on the ResultSet class for retrieving SQL SELECT results as Java types ",
                    "isAnswer": false
                },
                {
                    "id": 1056,
                    "questionId": 1010,
                    "name": " Methods on the PreparedStatement class for sending Java types as SQL statement parameters",
                    "isAnswer": false
                },
                {
                    "id": 1057,
                    "questionId": 1010,
                    "name": "  Methods on the CallableStatement class for retrieving SQL OUT parameters as Java types",
                    "isAnswer":false
                },
                {
                    "id": 1058,
                    "questionId": 1010,
                    "name": " All mentioned above ",
                    "isAnswer": true
                }
            ],
            "questionType": {
                "id": 1,
                "name": "Multiple Choice",
                "isActive": true
            }
        },
        {
            "id": 1011,
            "name": "The interface ResultSet has a method, getMetaData(), that returns a/an",
			"explanation": "no explanation",
            "questionTypeId": 1,
            "options": [
                {
                    "id": 1059,
                    "questionId": 1010,
                    "name": " Tuple",
                    "isAnswer": false
                },
                {
                    "id": 1060,
                    "questionId": 1010,
                    "name": "  Value ",
                    "isAnswer": false
                },
                {
                    "id": 1061,
                    "questionId": 1010,
                    "name": "  Object",
                    "isAnswer": true
                },
                {
                    "id": 1062,
                    "questionId": 1010,
                    "name": " Result",
                    "isAnswer": false
                }
            ],
            "questionType": {
                "id": 1,
                "name": "Multiple Choice",
                "isActive": true
            }
        },
        {
            "id": 1012,
            "name": " What is sent to the user via HTTP, invoked using the HTTP protocol on the user's computer, and run on the user's computer as an application?",
			"explanation": "no explanation",
            "questionTypeId": 1,
            "options": [
                {
                    "id": 1063,
                    "questionId": 1010,
                    "name": "A Java application",
                    "isAnswer": false
                },
                {
                    "id": 1064,
                    "questionId": 1010,
                    "name": "A Java applet",
                    "isAnswer": true
                },
                {
                    "id": 1065,
                    "questionId": 1010,
                    "name": "A Java servlet",
                    "isAnswer": false
                },
                {
                    "id": 1066,
                    "questionId": 1010,
                    "name": " None of the above is correct",
                    "isAnswer": false
                }
            ],
            "questionType": {
                "id": 1,
                "name": "Multiple Choice",
                "isActive": true
            }
        },
		{
			"id": 1013,
            "name": " Which methods returns a stream that simply provides the raw bytes from the database without any conversion?",
			"explanation": "no explanation",
            "questionTypeId": 1,
            "options": [
                {
                    "id": 1067,
                    "questionId": 1010,
                    "name": "getCharacterStream",
                    "isAnswer": false
                },
                {
                    "id": 1068,
                    "questionId": 1010,
                    "name": "getBinaryStream",
                    "isAnswer": true
                },
                {
                    "id": 1069,
                    "questionId": 1010,
                    "name": "getAsciiStream",
                    "isAnswer": false
                },
                {
                    "id": 1070,
                    "questionId": 1010,
                    "name": "getUnicodeStream ",
                    "isAnswer": false
                }
            ],
            "questionType": {
                "id": 1,
                "name": "Multiple Choice",
                "isActive": true
            }
		},
		{
			"id": 1014,
            "name": "In which of the following type of ResultSet, the cursor can scroll forwards and backwards, and the result set is sensitive to changes made by others to the database that occur after the result set was created?",
			"explanation": "no explanation",
            "questionTypeId": 1,
            "options": [
                {
                    "id": 1071,
                    "questionId": 1010,
                    "name": "ResultSet.TYPE_FORWARD_ONLY",
                    "isAnswer": false
                },
                {
                    "id": 1072,
                    "questionId": 1010,
                    "name": "ResultSet.TYPE_SCROLL_INSENSITIVE",
                    "isAnswer": false
                },
                {
                    "id": 1073,
                    "questionId": 1010,
                    "name": "ResultSet.TYPE_SCROLL_SENSITIVE",
                    "isAnswer": true
                },
                {
                    "id": 1074,
                    "questionId": 1010,
                    "name": "None of the above ",
                    "isAnswer": false
                }
            ],
            "questionType": {
                "id": 1,
                "name": "Multiple Choice",
                "isActive": true
            }
		},
		{
			"id": 1015,
            "name": "  Where is metadata stored in MySQL?",
			"explanation": " no explanation",
            "questionTypeId": 1,
            "options": [
                {
                    "id": 1075,
                    "questionId": 1010,
                    "name": " In the MySQL database metadata ",
                    "isAnswer": false
                },
                {
                    "id": 1076,
                    "questionId": 1010,
                    "name": "In the MySQL database metasql",
                    "isAnswer": false
                },
                {
                    "id": 1077,
                    "questionId": 1010,
                    "name": " In the MySQL database mysql",
                    "isAnswer": true
                },
                {
                    "id": 1078,
                    "questionId": 1010,
                    "name": "None of the above is correct",
                    "isAnswer": false
                }
            ],
            "questionType": {
                "id": 1,
                "name": "Multiple Choice",
                "isActive": true
            }
		},
		{
			"id": 1016,
            "name": "Which JDBC type represents a single precision floating point number that supports seven digits of mantissa?",
			"explanation": "no explanation",
            "questionTypeId": 1,
            "options": [
                {
                    "id": 1079,
                    "questionId": 1010,
                    "name": " Real",
                    "isAnswer": true
                },
                {
                    "id": 1080,
                    "questionId": 1010,
                    "name": "Double",
                    "isAnswer": false
                },
                {
                    "id": 1081,
                    "questionId": 1010,
                    "name": "Float",
                    "isAnswer": false
                },
                {
                    "id": 1082,
                    "questionId": 1010,
                    "name": " Integer",
                    "isAnswer": false
                }
            ],
            "questionType": {
                "id": 1,
                "name": "Multiple Choice",
                "isActive": true
            }
		},
		{
			"id": 1017,
            "name": "Which JDBC driver Type(s) can be used in either applet or servlet code?",
			"explanation": "no explanation ",
            "questionTypeId": 1,
            "options": [
                {
                    "id": 1083,
                    "questionId": 1010,
                    "name": " Both Type 1 and Type 2",
                    "isAnswer": false
                },
                {
                    "id": 1084,
                    "questionId": 1010,
                    "name": " Both Type 1 and Type 3 ",
                    "isAnswer": false
                },
                {
                    "id": 1085,
                    "questionId": 1010,
                    "name": "Both Type 3 and Type 4",
                    "isAnswer": true
                },
                {
                    "id": 1086,
                    "questionId": 1010,
                    "name": "Type 4 only",
                    "isAnswer": false
                }
            ],
            "questionType": {
                "id": 1,
                "name": "Multiple Choice",
                "isActive": true
            }
		},
		{
			"id": 1018,
            "name": "  Abbreviate the term UDA?",
			"explanation": " no explanation",
            "questionTypeId": 1,
            "options": [
                {
                    "id": 1087,
                    "questionId": 1010,
                    "name": "Unified Data Access",
                    "isAnswer": false
                },
                {
                    "id": 1088,
                    "questionId": 1010,
                    "name": "Universal Data Access",
                    "isAnswer": true
                },
                {
                    "id": 1089,
                    "questionId": 1010,
                    "name": "Universal Digital Access",
                    "isAnswer": false
                },
                {
                    "id": 1090,
                    "questionId": 1010,
                    "name": " Uniform Data Access ",
                    "isAnswer": false
                }
            ],
            "questionType": {
                "id": 1,
                "name": "Multiple Choice",
                "isActive": true
            }
		},
		{
			"id": 1019,
            "name": " Which one of the following contains date information? ",
			"explanation": "no explanation",
            "questionTypeId": 1,
            "options": [
                {
                    "id": 1091,
                    "questionId": 1010,
                    "name": "java.sql.TimeStamp ",
                    "isAnswer": true
                },
                {
                    "id": 1092,
                    "questionId": 1010,
                    "name": "java.sql.Time  ",
                    "isAnswer": false
                },
                {
                    "id": 1093,
                    "questionId": 1010,
                    "name": "java.io.Time",
                    "isAnswer": false
                },
                {
                    "id": 1094,
                    "questionId": 1010,
                    "name": "java.io.TimeStamp ",
                    "isAnswer": false
                }
            ],
            "questionType": {
                "id": 1,
                "name": "Multiple Choice",
                "isActive": true
            }
		}
    ]
}