{
    "id": 1,
    "name": "6th August 2020 Current Affairs Quiz",
    "description": "6th August 2020 Current Affairs Quiz",
    "questions": [
        {
            "id": 1010,
            "name": "Department of Defence, Ministry of Defence has signed a tripartite MoU with the Department of Administrative Reforms & Public Grievances (DARPG) and ________ ",
			"explanation": "",
            "questionTypeId": 1,
            "options": [
                {
                    "id": 1055,
                    "questionId": 1010,
                    "name": "Indian Institute of Technology, Kanpur  ",
                    "isAnswer": true
                },
                {
                    "id": 1056,
                    "questionId": 1010,
                    "name": " Indian Institute of Technology, Bombay ",
                    "isAnswer": false
                },
                {
                    "id": 1057,
                    "questionId": 1010,
                    "name": " Indian Institute of Technology, Madras",
                    "isAnswer":false
                },
                {
                    "id": 1058,
                    "questionId": 1010,
                    "name": " Indian Institute of Technology, Goa",
                    "isAnswer": false
                }
            ],
            "questionType": {
                "id": 1,
                "name": "Multiple Choice",
                "isActive": true
            }
        },
        {
            "id": 1011,
            "name": " Union Minister of Agriculture & Farmers’ Welfare has launched the Sahakar Cooptube NCDC Channel, a new initiative of?",
			"explanation": "Union Minister of Agriculture & Farmers’ Welfare has launched the Sahakar Cooptube NCDC Channel, a new initiative of National Cooperative Development Corporation",
            "questionTypeId": 1,
            "options": [
                {
                    "id": 1059,
                    "questionId": 1010,
                    "name": " National Cooperative Development Corporation ",
                    "isAnswer": true
                },
                {
                    "id": 1060,
                    "questionId": 1010,
                    "name": "  National Integration Council   ",
                    "isAnswer": false
                },
                {
                    "id": 1061,
                    "questionId": 1010,
                    "name": " National Development Council ",
                    "isAnswer": false
                },
                {
                    "id": 1062,
                    "questionId": 1010,
                    "name": " National Skill Development Corporation ",
                    "isAnswer": false
                }
            ],
            "questionType": {
                "id": 1,
                "name": "Multiple Choice",
                "isActive": true
            }
        },
        {
            "id": 1012,
            "name": " National Bank of _______ has selected the Infosys’ Finacle Cash Management Suite to digitally transform its transaction banking business.",
			"explanation": "National Bank of Bahrain and Infosys Finacle has selected the Infosys’ Finacle Cash Management Suite to digitally transform its transaction banking business",
            "questionTypeId": 1,
            "options": [
                {
                    "id": 1063,
                    "questionId": 1010,
                    "name": "Kuwait",
                    "isAnswer": false
                },
                {
                    "id": 1064,
                    "questionId": 1010,
                    "name": "Brunei ",
                    "isAnswer": false
                },
                {
                    "id": 1065,
                    "questionId": 1010,
                    "name": " Qatar",
                    "isAnswer": false
                },
                {
                    "id": 1066,
                    "questionId": 1010,
                    "name": " Bahrain",
                    "isAnswer": true
                }
            ],
            "questionType": {
                "id": 1,
                "name": "Multiple Choice",
                "isActive": true
            }
        },
		{
			"id": 1013,
            "name": " Name the former Real Madrid and Spain goalkeeper who has recently announced his retirement from football",
			"explanation": "Former Real Madrid and Spain goalkeeper Iker Casillas has announced his retirement from football",
            "questionTypeId": 1,
            "options": [
                {
                    "id": 1067,
                    "questionId": 1010,
                    "name": "Keylor Navas",
                    "isAnswer": false
                },
                {
                    "id": 1068,
                    "questionId": 1010,
                    "name": "Petr Cech",
                    "isAnswer": false
                },
                {
                    "id": 1069,
                    "questionId": 1010,
                    "name": "Sergio Ramos",
                    "isAnswer": false
                },
                {
                    "id": 1070,
                    "questionId": 1010,
                    "name": "Iker Casillas ",
                    "isAnswer": true
                }
            ],
            "questionType": {
                "id": 1,
                "name": "Multiple Choice",
                "isActive": true
            }
		},
		{
			"id": 1014,
            "name": "Name the person who has become the Prime Minister of Guyana",
			"explanation": "Mark Phillips has become the Prime Minister of Guyana",
            "questionTypeId": 1,
            "options": [
                {
                    "id": 1071,
                    "questionId": 1010,
                    "name": "Evariste Ndayishimiye",
                    "isAnswer": false
                },
                {
                    "id": 1072,
                    "questionId": 1010,
                    "name": "Keith Rowley",
                    "isAnswer": false
                },
                {
                    "id": 1073,
                    "questionId": 1010,
                    "name": "Chan Santokhi",
                    "isAnswer": false
                },
                {
                    "id": 1074,
                    "questionId": 1010,
                    "name": "Mark Phillips ",
                    "isAnswer": true
                }
            ],
            "questionType": {
                "id": 1,
                "name": "Multiple Choice",
                "isActive": true
            }
		},
		{
			"id": 1015,
            "name": "  When was the HDFC bank founded?",
			"explanation": "  HDFC Bank Limited is an Indian banking and financial services company headquartered in Mumbai, Maharashtra. It as established in August 1994. It is the largest bank in India by market capitalization as of March 2020",
            "questionTypeId": 1,
            "options": [
                {
                    "id": 1075,
                    "questionId": 1010,
                    "name": " 1990 ",
                    "isAnswer": false
                },
                {
                    "id": 1076,
                    "questionId": 1010,
                    "name": "1992",
                    "isAnswer": false
                },
                {
                    "id": 1077,
                    "questionId": 1010,
                    "name": "1994",
                    "isAnswer": true
                },
                {
                    "id": 1078,
                    "questionId": 1010,
                    "name": "1995",
                    "isAnswer": false
                }
            ],
            "questionType": {
                "id": 1,
                "name": "Multiple Choice",
                "isActive": true
            }
		},
		{
			"id": 1016,
            "name": "Vaishno Devi yatra will begin from which date?",
			"explanation": "Shri Mata Vaishno Devi Shrine Board has announced the resumption of Vaishno Devi yatra from August 16, 2020, almost four months after it was suspended because of the COVID-19 pandemic",
            "questionTypeId": 1,
            "options": [
                {
                    "id": 1079,
                    "questionId": 1010,
                    "name": "August 30th ",
                    "isAnswer": false
                },
                {
                    "id": 1080,
                    "questionId": 1010,
                    "name": "August 20th ",
                    "isAnswer": false
                },
                {
                    "id": 1081,
                    "questionId": 1010,
                    "name": "August 17th ",
                    "isAnswer": false
                },
                {
                    "id": 1082,
                    "questionId": 1010,
                    "name": "August 16th ",
                    "isAnswer": true
                }
            ],
            "questionType": {
                "id": 1,
                "name": "Multiple Choice",
                "isActive": true
            }
		},
		{
			"id": 1017,
            "name": " What is the cost of Favipiravir drug under the brand name Covihalt?",
			"explanation": "no explanation ",
            "questionTypeId": 1,
            "options": [
                {
                    "id": 1083,
                    "questionId": 1010,
                    "name": " Rs.64",
                    "isAnswer": false
                },
                {
                    "id": 1084,
                    "questionId": 1010,
                    "name": "Rs.55 ",
                    "isAnswer": false
                },
                {
                    "id": 1085,
                    "questionId": 1010,
                    "name": "Rs.49",
                    "isAnswer": true
                },
                {
                    "id": 1086,
                    "questionId": 1010,
                    "name": "Rs.24",
                    "isAnswer": false
                }
            ],
            "questionType": {
                "id": 1,
                "name": "Multiple Choice",
                "isActive": true
            }
		},
		{
			"id": 1018,
            "name": "  Which Chinese company pulled out as IPL's Title Sponsor?",
			"explanation": " Vivo, the Title Sponsor of the Indian Premier League 2020, has pulled out after a disagreement with the Board of Control for Cricket (BCCI) over a discount on the sponsorship fee and also in response to the growing opposition to its involvement in the tournament, as it is a Chinese brand",
            "questionTypeId": 1,
            "options": [
                {
                    "id": 1087,
                    "questionId": 1010,
                    "name": "Xiaomi",
                    "isAnswer": false
                },
                {
                    "id": 1088,
                    "questionId": 1010,
                    "name": "Oppo",
                    "isAnswer": false
                },
                {
                    "id": 1089,
                    "questionId": 1010,
                    "name": "Huawei",
                    "isAnswer": false
                },
                {
                    "id": 1090,
                    "questionId": 1010,
                    "name": "Vivo ",
                    "isAnswer": true
                }
            ],
            "questionType": {
                "id": 1,
                "name": "Multiple Choice",
                "isActive": true
            }
		},
		{
			"id": 1019,
            "name": " The Swachh Bharat Kranti expresses the journey of SBM through ________ essays by a diverse range of stakeholders and contributors to the SBM. ",
			"explanation": "The Swachh Bharat Kranti expresses the journey of the Swachh Bharat Mission (SBM) through 35 essays by a diverse range of stakeholders and contributors to the SBM.",
            "questionTypeId": 1,
            "options": [
                {
                    "id": 1091,
                    "questionId": 1010,
                    "name": "20 ",
                    "isAnswer": false
                },
                {
                    "id": 1092,
                    "questionId": 1010,
                    "name": "35  ",
                    "isAnswer": true
                },
                {
                    "id": 1093,
                    "questionId": 1010,
                    "name": "42",
                    "isAnswer": false
                },
                {
                    "id": 1094,
                    "questionId": 1010,
                    "name": "56  ",
                    "isAnswer": false
                }
            ],
            "questionType": {
                "id": 1,
                "name": "Multiple Choice",
                "isActive": true
            }
		}
    ]
}