{
    "id": 1,
    "name": "Andhra Pradesh GK Test 1",
    "description": "Practice Andhra Pradesh GK Online Test 1",
    "questions": [
        {
            "id": 1010,
            "name": "Total number of districts in Andhra Pradesh?",
			"explanation": "no explanation",
            "questionTypeId": 1,
            "options": [
                {
                    "id": 1055,
                    "questionId": 1010,
                    "name": "10",
                    "isAnswer": false
                },
                {
                    "id": 1056,
                    "questionId": 1010,
                    "name": "11",
                    "isAnswer": false
                },
                {
                    "id": 1057,
                    "questionId": 1010,
                    "name": "13",
                    "isAnswer": true
                },
                {
                    "id": 1058,
                    "questionId": 1010,
                    "name": "17",
                    "isAnswer": false
                }
            ],
            "questionType": {
                "id": 1,
                "name": "Multiple Choice",
                "isActive": true
            }
        },
        {
            "id": 1011,
            "name": "How long the Kakatiya dynasty existed?",
			"explanation": "",
            "questionTypeId": 1,
            "options": [
                {
                    "id": 1059,
                    "questionId": 1010,
                    "name": "From 1163 to 1323",
                    "isAnswer": true
                },
                {
                    "id": 1060,
                    "questionId": 1010,
                    "name": "From 1263 to 1323",
                    "isAnswer": false
                },
                {
                    "id": 1061,
                    "questionId": 1010,
                    "name": "From 1763 to 1823",
                    "isAnswer": false
                },
                {
                    "id": 1062,
                    "questionId": 1010,
                    "name": "From 1563 to 1623",
                    "isAnswer": false
                }
            ],
            "questionType": {
                "id": 1,
                "name": "Multiple Choice",
                "isActive": true
            }
        },
        {
            "id": 1012,
            "name": "Who built the Kondaveedu Fort?",
			"explanation": "no explanation",
            "questionTypeId": 1,
            "options": [
                {
                    "id": 1063,
                    "questionId": 1010,
                    "name": "Both Rajas of Orissa and Reddy dynasty in 13th century",
                    "isAnswer": true
                },
                {
                    "id": 1064,
                    "questionId": 1010,
                    "name": " Rajas of Orissa and Reddy dynasty in 15th century",
                    "isAnswer": false
                },
                {
                    "id": 1065,
                    "questionId": 1010,
                    "name": "Both Rajas of Orissa dynasty in 17th century",
                    "isAnswer": false
                },
                {
                    "id": 1066,
                    "questionId": 1010,
                    "name": "Both Rajas of Orissa and Reddy dynasty in 18th century",
                    "isAnswer": false
                }
            ],
            "questionType": {
                "id": 1,
                "name": "Multiple Choice",
                "isActive": true
            }
        },
		{
			"id": 1013,
            "name": "What is to the east of Andhra Pradesh ?",
			"explanation": "no explanation ",
            "questionTypeId": 1,
            "options": [
                {
                    "id": 1067,
                    "questionId": 1010,
                    "name": "Arabian Sea",
                    "isAnswer": false
                },
                {
                    "id": 1068,
                    "questionId": 1010,
                    "name": "Bay of Bengal",
                    "isAnswer": true
                },
                {
                    "id": 1069,
                    "questionId": 1010,
                    "name": "Gulf of Cambay",
                    "isAnswer": false
                },
                {
                    "id": 1070,
                    "questionId": 1010,
                    "name": " Palk Strait",
                    "isAnswer": false
                }
            ],
            "questionType": {
                "id": 1,
                "name": "Multiple Choice",
                "isActive": true
            }
		},
		{
			"id": 1014,
            "name": "Nagari is a Municipal town in ..... district of Andhra Pradesh?",
			"explanation": "no explanation",
            "questionTypeId": 1,
            "options": [
                {
                    "id": 1071,
                    "questionId": 1010,
                    "name": "Anantapur ",
                    "isAnswer": false
                },
                {
                    "id": 1072,
                    "questionId": 1010,
                    "name": "East Godavari",
                    "isAnswer":false
                },
                {
                    "id": 1073,
                    "questionId": 1010,
                    "name": " Chittoor",
                    "isAnswer":true
                },
                {
                    "id": 1074,
                    "questionId": 1010,
                    "name": "Guntur",
                    "isAnswer": false
                }
            ],
            "questionType": {
                "id": 1,
                "name": "Multiple Choice",
                "isActive": true
            }
		},
		{
			"id": 1015,
            "name": "The Saidani Maa Ki Dargah was constructed in ..... AD ?",
			"explanation": "no explanation",
            "questionTypeId": 1,
            "options": [
                {
                    "id": 1075,
                    "questionId": 1010,
                    "name": "1881",
                    "isAnswer": false
                },
                {
                    "id": 1076,
                    "questionId": 1010,
                    "name": "1882",
                    "isAnswer":false
                },
                {
                    "id": 1077,
                    "questionId": 1010,
                    "name": "1883",
                    "isAnswer":true
                },
                {
                    "id": 1078,
                    "questionId": 1010,
                    "name": "1884",
                    "isAnswer": false
                }
            ],
            "questionType": {
                "id": 1,
                "name": "Multiple Choice",
                "isActive": true
            }
		},
		{
			"id": 1016,
            "name": "Where is Amareswara temple dedicated to Lord Shiva located ?",
			"explanation": "no explanation",
            "questionTypeId": 1,
            "options": [
                {
                    "id": 1079,
                    "questionId": 1010,
                    "name": "Hyderabad ",
                    "isAnswer": false
                },
                {
                    "id": 1080,
                    "questionId": 1010,
                    "name": "Vijayawada",
                    "isAnswer": false
                },
                {
                    "id": 1081,
                    "questionId": 1010,
                    "name": "Amaravathi ",
                    "isAnswer": true
                },
                {
                    "id": 1082,
                    "questionId": 1010,
                    "name": "Anantapur ",
                    "isAnswer":false
                }
            ],
            "questionType": {
                "id": 1,
                "name": "Multiple Choice",
                "isActive": true
            }
		},
		{
			"id": 1017,
            "name": "Who among the following was the author of Musalamma Maranamu?",
			"explanation": "no explanation",
            "questionTypeId": 1,
            "options": [
                {
                    "id": 1083,
                    "questionId": 1010,
                    "name": "CR Reddy",
                    "isAnswer": true
                },
                {
                    "id": 1084,
                    "questionId": 1010,
                    "name": "Anandacharyulu",
                    "isAnswer":false
                },
                {
                    "id": 1085,
                    "questionId": 1010,
                    "name": "Rayaprolu Subbarao",
                    "isAnswer": false
                },
                {
                    "id": 1086,
                    "questionId": 1010,
                    "name": "Jiddu Krishnamurti ",
                    "isAnswer": false
                }
            ],
            "questionType": {
                "id": 1,
                "name": "Multiple Choice",
                "isActive": true
            }
		},
		{
			"id": 1018,
            "name": "Polavaram Irrigation Project was declared as National Project under which section of the AP reorganization act?",
			"explanation": "no explanation",
            "questionTypeId": 1,
            "options": [
                {
                    "id": 1087,
                    "questionId": 1010,
                    "name": "Section 50 ",
                    "isAnswer": false
                },
                {
                    "id": 1088,
                    "questionId": 1010,
                    "name": "Section 86",
                    "isAnswer": false
                },
                {
                    "id": 1089,
                    "questionId": 1010,
                    "name": "Section 90 ",
                    "isAnswer": true
                },
                {
                    "id": 1090,
                    "questionId": 1010,
                    "name": "Section 92 ",
                    "isAnswer": false
                }
            ],
            "questionType": {
                "id": 1,
                "name": "Multiple Choice",
                "isActive": true
            }
		},
		{
			"id": 1019,
            "name": " When was Andhra Pradesh formed?",
			"explanation": "no explanation",
            "questionTypeId": 1,
            "options": [
                {
                    "id": 1091,
                    "questionId": 1010,
                    "name": "04 March 1937 ",
                    "isAnswer": false
                },
                {
                    "id": 1092,
                    "questionId": 1010,
                    "name": "08 June 1951 ",
                    "isAnswer":false
                },
                {
                    "id": 1093,
                    "questionId": 1010,
                    "name": "12 July 1949 ",
                    "isAnswer": false
                },
                {
                    "id": 1094,
                    "questionId": 1010,
                    "name": "01 October 1953",
                    "isAnswer": true
                }
            ],
            "questionType": {
                "id": 1,
                "name": "Multiple Choice",
                "isActive": true
            }
		}
    ]
}