{
    "id": 1,
    "name": "Sqoop Quiz 2",
    "description": "Sqoop Quiz 2",
    "questions": [
        {
            "id": 1010,
            "name": "While SequenceFile stores each record as key-value pair, the avro system stored records as",
			"explanation": "no explanation",
            "questionTypeId": 1,
            "options": [
                {
                    "id": 1055,
                    "questionId": 1010,
                    "name": "Simple text ",
                    "isAnswer": false
                },
                {
                    "id": 1056,
                    "questionId": 1010,
                    "name": " chained lists",
                    "isAnswer": false
                },
                {
                    "id": 1057,
                    "questionId": 1010,
                    "name": " Linked lists",
                    "isAnswer":false
                },
                {
                    "id": 1058,
                    "questionId": 1010,
                    "name": " schema and data ",
                    "isAnswer": true
                }
            ],
            "questionType": {
                "id": 1,
                "name": "Multiple Choice",
                "isActive": true
            }
        },
        {
            "id": 1011,
            "name": "  What are the two different incremental modes of importing data into sqoop?",
			"explanation": "no explanation",
            "questionTypeId": 1,
            "options": [
                {
                    "id": 1059,
                    "questionId": 1010,
                    "name": " merge and add ",
                    "isAnswer": false
                },
                {
                    "id": 1060,
                    "questionId": 1010,
                    "name": " append and modified  ",
                    "isAnswer": false
                },
                {
                    "id": 1061,
                    "questionId": 1010,
                    "name": " merge and lastmodified ",
                    "isAnswer": false
                },
                {
                    "id": 1062,
                    "questionId": 1010,
                    "name": " append and lastmodified",
                    "isAnswer": true
                }
            ],
            "questionType": {
                "id": 1,
                "name": "Multiple Choice",
                "isActive": true
            }
        },
        {
            "id": 1012,
            "name": " What is achieved by using the --meta-connect parameter in a sqoop command?",
			"explanation": "no explanation",
            "questionTypeId": 1,
            "options": [
                {
                    "id": 1063,
                    "questionId": 1010,
                    "name": "run metastore as a service accessible remotely",
                    "isAnswer": true
                },
                {
                    "id": 1064,
                    "questionId": 1010,
                    "name": "run metastore as a service accessible locally",
                    "isAnswer": false
                },
                {
                    "id": 1065,
                    "questionId": 1010,
                    "name": "  connect to the meastore tables",
                    "isAnswer": false
                },
                {
                    "id": 1066,
                    "questionId": 1010,
                    "name": "connect to the metadata of the external relational tables form which data has to be imported",
                    "isAnswer": false
                }
            ],
            "questionType": {
                "id": 1,
                "name": "Multiple Choice",
                "isActive": true
            }
        },
		{
			"id": 1013,
            "name": " When does sqoop gather the metadata of the relational table into which it exports the data?",
			"explanation": "no explanation",
            "questionTypeId": 1,
            "options": [
                {
                    "id": 1067,
                    "questionId": 1010,
                    "name": "Gathers the metadata of all tables only once during establishing the connection to the database",
                    "isAnswer": false
                },
                {
                    "id": 1068,
                    "questionId": 1010,
                    "name": " Never as it relies on the user to ensure the exported data matches the table’s structure",
                    "isAnswer": false
                },
                {
                    "id": 1069,
                    "questionId": 1010,
                    "name": "Every time the sqoop export command it submitted and just before the data transfer starts",
                    "isAnswer": true
                },
                {
                    "id": 1070,
                    "questionId": 1010,
                    "name": "Only if the export fails, Sqoop accesses the metadata of the table ",
                    "isAnswer": false
                }
            ],
            "questionType": {
                "id": 1,
                "name": "Multiple Choice",
                "isActive": true
            }
		},
		{
			"id": 1014,
            "name": " The insert query used to insert exported data into tables is generate by",
			"explanation": "no explanation",
            "questionTypeId": 1,
            "options": [
                {
                    "id": 1071,
                    "questionId": 1010,
                    "name": "Sqoop command and processed as such",
                    "isAnswer": true
                },
                {
                    "id": 1072,
                    "questionId": 1010,
                    "name": " Sqoop command and modified suitably by JDBC drive",
                    "isAnswer": false
                },
                {
                    "id": 1073,
                    "questionId": 1010,
                    "name": "JDBC driver",
                    "isAnswer": false
                },
                {
                    "id": 1074,
                    "questionId": 1010,
                    "name": "Database specific driver ",
                    "isAnswer": false
                }
            ],
            "questionType": {
                "id": 1,
                "name": "Multiple Choice",
                "isActive": true
            }
		},
		{
			"id": 1015,
            "name": "  When using –update-mode allowinsert parameter with oracle database the feature of oracle used by sqoop is",
			"explanation": " no explanation",
            "questionTypeId": 1,
            "options": [
                {
                    "id": 1075,
                    "questionId": 1010,
                    "name": " UPSERT statement ",
                    "isAnswer": false
                },
                {
                    "id": 1076,
                    "questionId": 1010,
                    "name": " MERGE statement",
                    "isAnswer": true
                },
                {
                    "id": 1077,
                    "questionId": 1010,
                    "name": "MULTITABLE INSERT statement",
                    "isAnswer": false
                },
                {
                    "id": 1078,
                    "questionId": 1010,
                    "name": "BULK LOAD statement",
                    "isAnswer": false
                }
            ],
            "questionType": {
                "id": 1,
                "name": "Multiple Choice",
                "isActive": true
            }
		},
		{
			"id": 1016,
            "name": "The parameter which can be used in place of --table parameter to insert data into table is",
			"explanation": "no explanation",
            "questionTypeId": 1,
            "options": [
                {
                    "id": 1079,
                    "questionId": 1010,
                    "name": "call",
                    "isAnswer": true
                },
                {
                    "id": 1080,
                    "questionId": 1010,
                    "name": "insert-into",
                    "isAnswer": false
                },
                {
                    "id": 1081,
                    "questionId": 1010,
                    "name": "populate",
                    "isAnswer": false
                },
                {
                    "id": 1082,
                    "questionId": 1010,
                    "name": "load-into",
                    "isAnswer": false
                }
            ],
            "questionType": {
                "id": 1,
                "name": "Multiple Choice",
                "isActive": true
            }
		},
		{
			"id": 1017,
            "name": " During import to hive using sqoop the data is",
			"explanation": "no explanation ",
            "questionTypeId": 1,
            "options": [
                {
                    "id": 1083,
                    "questionId": 1010,
                    "name": "  directly loaded to existing hive table",
                    "isAnswer": false
                },
                {
                    "id": 1084,
                    "questionId": 1010,
                    "name": "first moved into a hive directory as a hdfs file ",
                    "isAnswer": true
                },
                {
                    "id": 1085,
                    "questionId": 1010,
                    "name": "first moved into any temporary location as a HDFS file",
                    "isAnswer": false
                },
                {
                    "id": 1086,
                    "questionId": 1010,
                    "name": "First validated against the table schema in hive",
                    "isAnswer": false
                }
            ],
            "questionType": {
                "id": 1,
                "name": "Multiple Choice",
                "isActive": true
            }
		},
		{
			"id": 1018,
            "name": " The parameter --hive-import can be used with",
			"explanation": " no explanation",
            "questionTypeId": 1,
            "options": [
                {
                    "id": 1087,
                    "questionId": 1010,
                    "name": "only importing to hive",
                    "isAnswer": false
                },
                {
                    "id": 1088,
                    "questionId": 1010,
                    "name": " importing to hive as well as text file",
                    "isAnswer": true
                },
                {
                    "id": 1089,
                    "questionId": 1010,
                    "name": "importing to hive and relational tables",
                    "isAnswer": false
                },
                {
                    "id": 1090,
                    "questionId": 1010,
                    "name": "importing to hive and binary data ",
                    "isAnswer": false
                }
            ],
            "questionType": {
                "id": 1,
                "name": "Multiple Choice",
                "isActive": true
            }
		},
		{
			"id": 1019,
            "name": " The sqoop export/import jobs canbe stored and used again and again by using ",
			"explanation": "no explanation",
            "questionTypeId": 1,
            "options": [
                {
                    "id": 1091,
                    "questionId": 1010,
                    "name": "sqoop- jobname ",
                    "isAnswer": false
                },
                {
                    "id": 1092,
                    "questionId": 1010,
                    "name": " sqoop-save-job  ",
                    "isAnswer": false
                },
                {
                    "id": 1093,
                    "questionId": 1010,
                    "name": "Sqoop-all-jobs",
                    "isAnswer": false
                },
                {
                    "id": 1094,
                    "questionId": 1010,
                    "name": "sqoop-job ",
                    "isAnswer": true
                }
            ],
            "questionType": {
                "id": 1,
                "name": "Multiple Choice",
                "isActive": true
            }
		}
    ]
}